redpysdk/__init__.py
redpysdk/http_utils.py
redpysdk/math_utils.py
redpysdk/pedersen_params.json
redpysdk/settings.py
redpysdk/signature.py
redpysdk/starkex_message.py
redpysdk/starkex_utils.py
red_py_sdk-0.1.10.dist-info/LICENSE
red_py_sdk-0.1.10.dist-info/METADATA
red_py_sdk-0.1.10.dist-info/WHEEL
red_py_sdk-0.1.10.dist-info/top_level.txt
red_py_sdk-0.1.10.dist-info/RECORD
