Metadata-Version: 2.1
Name: red-py-sdk
Version: 0.1.10
Summary: https://github.com/reddio-com/red-py-sdk
Home-page: https://github.com/reddio-com/red-py-sdk
Author: Reddio
Author-email: contact@reddio.com
Keywords: reddio sdk
Classifier: Programming Language :: Python :: 3
Classifier: Topic :: Education
Classifier: Topic :: Software Development :: Internationalization
Classifier: Topic :: Utilities
Classifier: License :: OSI Approved :: GNU General Public License v3 (GPLv3)
Classifier: Operating System :: OS Independent
License-File: LICENSE
Requires-Dist: mpmath
Requires-Dist: ecdsa
Requires-Dist: sympy
Requires-Dist: web3
